examples/Complete_1.py
examples/Search_1.py
examples/__init__.py
goldpot/CompletionEnginesConfig.py
goldpot/CompletionPromptConfig.py
goldpot/Config.py
goldpot/DefaultConfig.py
goldpot/Goldpot.py
goldpot/Model.py
goldpot/Utils.py
goldpot/__init__.py
goldpot-0.0.3.4.dist-info/LICENSE
goldpot-0.0.3.4.dist-info/METADATA
goldpot-0.0.3.4.dist-info/WHEEL
goldpot-0.0.3.4.dist-info/top_level.txt
goldpot-0.0.3.4.dist-info/RECORD
