Metadata-Version: 2.1
Name: goldpot
Version: 0.0.3.4
Summary: A thin convenience layer on top of OpenAI's GPT-3 Python library
Home-page: https://github.com/ssenge/Goldpot
Author: Sebastian Senge
Author-email: ssenge.public@gmail.com
License: UNKNOWN
Platform: UNKNOWN
Classifier: Programming Language :: Python :: 3
Classifier: License :: OSI Approved :: GNU General Public License v3 (GPLv3)
Classifier: Operating System :: OS Independent
Requires-Python: >=3.7
